PY_4/__init__.py
PY_4/command_parser.py
PY_4/crawler.py
PY_4/helpcode.py
PY_4/metadata.py
PY_4/representation.py
PY_4/storage.py
PY_4/website_stats.py
pycrawler_04-0.0.1.dist-info/LICENSE.txt
pycrawler_04-0.0.1.dist-info/METADATA
pycrawler_04-0.0.1.dist-info/WHEEL
pycrawler_04-0.0.1.dist-info/top_level.txt
pycrawler_04-0.0.1.dist-info/RECORD
