Metadata-Version: 2.1
Name: pycrawler-04
Version: 0.0.1
Summary: A crawler
Home-page: https://git.corp.adobe.com/yanand/PY_4
Author: palak_agrawal
Author-email: palakagrawaljk@gmail.com
License: UNKNOWN
Platform: UNKNOWN
Classifier: Programming Language :: Python :: 3
Classifier: License :: OSI Approved :: MIT License
Classifier: Operating System :: OS Independent
Requires-Python: >=3.6
